[
  {
    "endpoint": "/api/v3/properties/d13bae15-9f1b-4df7-b1ac-e58fc56bde4d",
    "total_requests": 21,
    "total_errors": 21,
    "client_errors_4xx": 21,
    "server_errors_5xx": 0,
    "keyword_errors": 0,
    "error_rate": 100.0,
    "is_critical": false,
    "timestamp": "2025-12-19T21:00:22.869373",
    "avg_response_time": null,
    "max_response_time": null,
    "min_response_time": null,
    "unique_clients": 0,
    "method": null
  },
  {
    "endpoint": "/api/v3/properties/d13bae15-9f1b-4df7-b1ac-e58fc56bde4d",
    "total_requests": 21,
    "total_errors": 21,
    "client_errors_4xx": 21,
    "server_errors_5xx": 0,
    "keyword_errors": 0,
    "error_rate": 100.0,
    "is_critical": false,
    "timestamp": "2025-12-19T21:00:22.869373",
    "avg_response_time": null,
    "max_response_time": null,
    "min_response_time": null,
    "unique_clients": 0,
    "method": null
  },
  {
    "endpoint": "/api/v3/properties/d13bae15-9f1b-4df7-b1ac-e58fc56bde4d",
    "total_requests": 21,
    "total_errors": 21,
    "client_errors_4xx": 21,
    "server_errors_5xx": 0,
    "keyword_errors": 0,
    "error_rate": 100.0,
    "is_critical": false,
    "timestamp": "2025-12-19T21:03:27.425528",
    "avg_response_time": null,
    "max_response_time": null,
    "min_response_time": null,
    "unique_clients": 0,
    "method": null
  },
  {
    "endpoint": "/api/v3/properties/d13bae15-9f1b-4df7-b1ac-e58fc56bde4d",
    "total_requests": 21,
    "total_errors": 21,
    "client_errors_4xx": 21,
    "server_errors_5xx": 0,
    "keyword_errors": 0,
    "error_rate": 100.0,
    "is_critical": false,
    "timestamp": "2025-12-19T21:03:27.425528",
    "avg_response_time": null,
    "max_response_time": null,
    "min_response_time": null,
    "unique_clients": 0,
    "method": null
  }
]